PatternTuring/__init__.py
PatternTuring/tucom4.py
PatternTuring-0.2.dist-info/METADATA
PatternTuring-0.2.dist-info/WHEEL
PatternTuring-0.2.dist-info/top_level.txt
PatternTuring-0.2.dist-info/RECORD
